pylunch/README.md
pylunch/__init__.py
pylunch/bots/__init__.py
pylunch/bots/dc_bot.py
pylunch/bots/telegram_bot.py
pylunch/cli.py
pylunch/config.py
pylunch/errors.py
pylunch/log_config.py
pylunch/lunch.py
pylunch/static/default.js
pylunch/static/img/dish.png
pylunch/static/img/dish.svg
pylunch/static/style.css
pylunch/tags_evaluator.py
pylunch/templates/.gitkeep
pylunch/templates/admin/edit.html
pylunch/templates/admin/erestaurants.html
pylunch/templates/admin/index.html
pylunch/templates/admin/login.html
pylunch/templates/error.html
pylunch/templates/fmenu.html
pylunch/templates/index.html
pylunch/templates/menu.html
pylunch/templates/restaurant.html
pylunch/templates/template.html
pylunch/utils.py
pylunch/web.py
pylunch-0.2.9.dist-info/entry_points.txt
pylunch-0.2.9.dist-info/WHEEL
pylunch-0.2.9.dist-info/METADATA
pylunch-0.2.9.dist-info/RECORD
