Metadata-Version: 2.1
Name: pylunch
Version: 0.2.9
Summary: Pylunch cli and web tool to get lunch info
Home-page: https://gitlab.com/pestanko/pylunch
License: Apache-2.0
Author: Peter Stanko
Author-email: peter.stanko0@gmail.com
Requires-Python: >=3.6,<4.0
Classifier: Intended Audience :: Developers
Classifier: License :: OSI Approved :: Apache Software License
Classifier: Operating System :: OS Independent
Classifier: Programming Language :: Python :: 3
Classifier: Programming Language :: Python :: 3.6
Classifier: Programming Language :: Python :: 3.7
Classifier: Programming Language :: Python :: 3.8
Classifier: Topic :: Utilities
Requires-Dist: aiodns
Requires-Dist: aiohttp
Requires-Dist: beautifulsoup4
Requires-Dist: click
Requires-Dist: discord.py (>=1.3,<2.0)
Requires-Dist: flask
Requires-Dist: flask-jwt-extended
Requires-Dist: fuzzywuzzy
Requires-Dist: gunicorn (>=19.9,<20.0)
Requires-Dist: html2text
Requires-Dist: ipython
Requires-Dist: lxml
Requires-Dist: pdfminer-six
Requires-Dist: pillow
Requires-Dist: pytesseract
Requires-Dist: python-levenshtein
Requires-Dist: python-telegram-bot (>=12.0.0b1,<13.0.0)
Requires-Dist: pyyaml
Requires-Dist: pyzomato
Requires-Dist: requests
Requires-Dist: toml (>=0.10.0,<0.11.0)
Requires-Dist: unidecode
Requires-Dist: werkzeug
Project-URL: Documentation, https://gitlab.com/pestanko/pylunch
Project-URL: Repository, https://gitlab.com/pestanko/pylunch
